clier
test
