Metadata-Version: 1.2
Name: clier
Version: 0.2
Summary: Makes interactive cli programs of modules
Home-page: https://github.com/DaniloZZZ/clier
License: MIT
Platform: UNKNOWN
Requires-Python: >=3.7
